Workbook

Sheet Resumen
A1: Resumen de Negocio
A2: Total vendido | B2: =Ventas!F1002 -> 8840
A3: Dinero para resurtir | B3: =Ventas!G1002 -> 6529.0914
A4: Ganancia pura | B4: =Ventas!H1002 -> 2310.9086
A5: Fernando | B5: =Reparto!D1002 -> 770.31
A6: Roberto | B6: =Reparto!E1002 -> 770.31
A7: Isak | B7: =Reparto!F1002 -> 770.28859

Sheet Productos
A1: ID | B1: Producto | C1: Lotes | D1: Piezas por producto | E1: Costo por producto | F1: Costo por pieza | G1: Precio al público | H1: Stock inicial | I1: Stock actual | J1: Estado
A2: =IF(B2="","","P"&TEXT(ROW()-1,"000")) -> P001 | B2: AN ABE ENERGY DRINK 11.2 OZ 12PK TANG ORANGE | C2: 1 | D2: 12 | E2: 540 | F2: =IF(OR(E2="",D2="",D2=0),"",E2/D2) -> 45 | G2: =IF(F2="","",ROUND(F2*1.33,0)) -> 60 | H2: 0 | I2: =IF($B2="","",H2-IF(Ventas!D2="",0,Ventas!D2)) -> 0 | J2: =IF($B2="","",IF(N(I2)=0,"Agotado","Activo")) -> Agotado
A3: =IF(B3="","","P"&TEXT(ROW()-1,"000")) -> P002 | B3: ARMADA ASHWAGANDHA + L-TEANINA 600 MG 90 CAPS | C3: 1 | D3: 1 | E3: 280 | F3: =IF(OR(E3="",D3="",D3=0),"",E3/D3) -> 280 | G3: 350 | H3: 1 | I3: =IF($B3="","",H3-IF(Ventas!D3="",0,Ventas!D3)) -> 1 | J3: =IF($B3="","",IF(N(I3)=0,"Agotado","Activo")) -> Activo
A4: =IF(B4="","","P"&TEXT(ROW()-1,"000")) -> P003 | B4: ARMADA CITRATO DE MAGNESIO 1000 MG 100 CAPS | C4: 1 | D4: 1 | E4: 260 | F4: =IF(OR(E4="",D4="",D4=0),"",E4/D4) -> 260 | G4: 350 | H4: 1 | I4: =IF($B4="","",H4-IF(Ventas!D4="",0,Ventas!D4)) -> 1 | J4: =IF($B4="","",IF(N(I4)=0,"Agotado","Activo")) -> Activo
A5: =IF(B5="","","P"&TEXT(ROW()-1,"000")) -> P004 | B5: BEBIDA CELSIUS | C5: 1 | D5: 12 | E5: 600 | F5: =IF(OR(E5="",D5="",D5=0),"",E5/D5) -> 50 | G5: 70 | H5: 14 | I5: =IF($B5="","",H5-IF(Ventas!D5="",0,Ventas!D5)) -> 12 | J5: =IF($B5="","",IF(N(I5)=0,"Agotado","Activo")) -> Activo
A6: =IF(B6="","","P"&TEXT(ROW()-1,"000")) -> P005 | B6: BLOOM 25 SERV PAQUETE | C6: 1 | D6: 1 | E6: 400 | F6: =IF(OR(E6="",D6="",D6=0),"",E6/D6) -> 400 | G6: 450 | H6: 1 | I6: =IF($B6="","",H6-IF(Ventas!D6="",0,Ventas!D6)) -> 1 | J6: =IF($B6="","",IF(N(I6)=0,"Agotado","Activo")) -> Activo
A7: =IF(B7="","","P"&TEXT(ROW()-1,"000")) -> P006 | B7: BLOOM SPAERKALING ENERGY 12OZ PEACH WATERMELON | C7: 1 | D7: 12 | E7: 542 | F7: =IF(OR(E7="",D7="",D7=0),"",E7/D7) -> 45.166667 | G7: 65 | H7: 0 | I7: =IF($B7="","",H7-IF(Ventas!D7="",0,Ventas!D7)) -> 0 | J7: =IF($B7="","",IF(N(I7)=0,"Agotado","Activo")) -> Agotado
A8: =IF(B8="","","P"&TEXT(ROW()-1,"000")) -> P007 | B8: BLOOM SPARKLING ENERGY 12OZ PEACH MANGO | C8: 1 | D8: 12 | E8: 542 | F8: =IF(OR(E8="",D8="",D8=0),"",E8/D8) -> 45.166667 | G8: 65 | H8: 0 | I8: =IF($B8="","",H8-IF(Ventas!D8="",0,Ventas!D8)) -> 0 | J8: =IF($B8="","",IF(N(I8)=0,"Agotado","Activo")) -> Agotado
A9: =IF(B9="","","P"&TEXT(ROW()-1,"000")) -> P008 | B9: BLOOM SPEARKLING ENERGY 12OZ PEACH LEMONS | C9: 1 | D9: 12 | E9: 542 | F9: =IF(OR(E9="",D9="",D9=0),"",E9/D9) -> 45.166667 | G9: 65 | H9: 0 | I9: =IF($B9="","",H9-IF(Ventas!D9="",0,Ventas!D9)) -> 0 | J9: =IF($B9="","",IF(N(I9)=0,"Agotado","Activo")) -> Agotado
A10: =IF(B10="","","P"&TEXT(ROW()-1,"000")) -> P009 | B10: BLOOM SURTIDO | C10: 1 | D10: 12 | E10: 550 | F10: =IF(OR(E10="",D10="",D10=0),"",E10/D10) -> 45.833333 | G10: 65 | H10: 11 | I10: =IF($B10="","",H10-IF(Ventas!D10="",0,Ventas!D10)) -> 1 | J10: =IF($B10="","",IF(N(I10)=0,"Agotado","Activo")) -> Activo
A11: =IF(B11="","","P"&TEXT(ROW()-1,"000")) -> P010 | B11: BSN NO-XPLODE VASO PUMP 24 SERV PINEAPPLE PUMP | C11: 1 | D11: 1 | E11: 411 | F11: =IF(OR(E11="",D11="",D11=0),"",E11/D11) -> 411 | G11: 600 | H11: 1 | I11: =IF($B11="","",H11-IF(Ventas!D11="",0,Ventas!D11)) -> 1 | J11: =IF($B11="","",IF(N(I11)=0,"Agotado","Activo")) -> Activo
A12: =IF(B12="","","P"&TEXT(ROW()-1,"000")) -> P011 | B12: BSN PROTEIN CRIPS 12 BARS VANILLA MARSHMALLOW *OFERTA* | C12: 1 | D12: 12 | E12: 600 | F12: =IF(OR(E12="",D12="",D12=0),"",E12/D12) -> 50 | G12: 65 | H12: 12 | I12: =IF($B12="","",H12-IF(Ventas!D12="",0,Ventas!D12)) -> 0 | J12: =IF($B12="","",IF(N(I12)=0,"Agotado","Activo")) -> Agotado
A13: =IF(B13="","","P"&TEXT(ROW()-1,"000")) -> P012 | B13: CBUM ESSENTIAL PWO 30 SERV BLUE RASPBERRY | C13: 1 | D13: 30 | E13: 410 | F13: =IF(OR(E13="",D13="",D13=0),"",E13/D13) -> 13.666667 | G13: 25 | H13: 0 | I13: =IF($B13="","",H13-IF(Ventas!D13="",0,Ventas!D13)) -> 0 | J13: =IF($B13="","",IF(N(I13)=0,"Agotado","Activo")) -> Agotado
A14: =IF(B14="","","P"&TEXT(ROW()-1,"000")) -> P013 | B14: CBUM ESSENTIAL PWO 30 SERV GUAVA | C14: 1 | D14: 1 | E14: 355 | F14: =IF(OR(E14="",D14="",D14=0),"",E14/D14) -> 355 | G14: 500 | H14: 0 | I14: =IF($B14="","",H14-IF(Ventas!D14="",0,Ventas!D14)) -> 0 | J14: =IF($B14="","",IF(N(I14)=0,"Agotado","Activo")) -> Agotado
... A16: =IF(B16="","","P"&TEXT(ROW()-1,"000")) -> P015 | B16: CBUM ESSENTIAL PWO 30SER GUAVA FRUIT | C16: 1 | D16: 21 | E16: 400 | F16: =IF(OR(E16="",D16="",D16=0),"",E16/D16) -> 19.047619 | G16: 25 | H16: 0 | I16: =IF($B16="","",H16-IF(Ventas!D16="",0,Ventas!D16)) -> 0 | J16: =IF($B16="","",IF(N(I16)=0,"Agotado","Activo")) -> Agotado
A17: =IF(B17="","","P"&TEXT(ROW()-1,"000")) -> P016 | B17: CREATINA BIRDMAN | C17: 1 | D17: 2 | E17: 780 | F17: =IF(OR(E17="",D17="",D17=0),"",E17/D17) -> 390 | G17: 430 | H17: 3 | I17: 3 | J17: =IF($B17="","",IF(N(I17)=0,"Agotado","Activo")) -> Activo
A18: =IF(B18="","","P"&TEXT(ROW()-1,"000")) -> P017 | B18: CREATINA BIRDMAN CON ELECTROLIT | C18: 1 | D18: 1 | E18: 350 | F18: =IF(OR(E18="",D18="",D18=0),"",E18/D18) -> 350 | G18: 430 | H18: 2 | I18: =IF($B18="","",H18-IF(Ventas!D18="",0,Ventas!D18)) -> 1 | J18: =IF($B18="","",IF(N(I18)=0,"Agotado","Activo")) -> Activo
A19: =IF(B19="","","P"&TEXT(ROW()-1,"000")) -> P018 | B19: CREATINA DRAGON PHARMA MONOHYDRATE 1KG | C19: 1 | D19: 1 | E19: 458 | F19: =IF(OR(E19="",D19="",D19=0),"",E19/D19) -> 458 | G19: 700 | H19: 2 | I19: =IF($B19="","",H19-IF(Ventas!D19="",0,Ventas!D19)) -> 2 | J19: =IF($B19="","",IF(N(I19)=0,"Agotado","Activo")) -> Activo
A20: =IF(B20="","","P"&TEXT(ROW()-1,"000")) -> P019 | B20: CREATINA DRAGON PHARMACREATINE MONOHYDRATE 300 GRS UNFLAVORED | C20: 1 | D20: 1 | E20: 300 | F20: =IF(OR(E20="",D20="",D20=0),"",E20/D20) -> 300 | G20: 400 | H20: 0 | I20: =IF($B20="","",H20-IF(Ventas!D20="",0,Ventas!D20)) -> 0 | J20: =IF($B20="","",IF(N(I20)=0,"Agotado","Activo")) -> Agotado
A21: =IF(B21="","","P"&TEXT(ROW()-1,"000")) -> P020 | B21: CREATINA MONOHIDRATADA CAT 300GR | C21: 1 | D21: 1 | E21: 320 | F21: =IF(OR(E21="",D21="",D21=0),"",E21/D21) -> 320 | G21: 350 | H21: 1 | I21: =IF($B21="","",H21-IF(Ventas!D21="",0,Ventas!D21)) -> 1 | J21: =IF($B21="","",IF(N(I21)=0,"Agotado","Activo")) -> Activo
A22: =IF(B22="","","P"&TEXT(ROW()-1,"000")) -> P021 | B22: CREATINA MONOHYDRATADA CAT 1000GR | C22: 1 | D22: 1 | E22: 610 | F22: =IF(OR(E22="",D22="",D22=0),"",E22/D22) -> 610 | G22: 700 | H22: 2 | I22: =IF($B22="","",H22-IF(Ventas!D22="",0,Ventas!D22)) -> 2 | J22: =IF($B22="","",IF(N(I22)=0,"Agotado","Activo")) -> Activo
A23: =IF(B23="","","P"&TEXT(ROW()-1,"000")) -> P022 | B23: DIPS DRAGON PHARMA | C23: 1 | D23: 1 | E23: 188 | F23: =IF(OR(E23="",D23="",D23=0),"",E23/D23) -> 188 | G23: 280 | H23: 4 | I23: =IF($B23="","",H23-IF(Ventas!D23="",0,Ventas!D23)) -> 4 | J23: =IF($B23="","",IF(N(I23)=0,"Agotado","Activo")) -> Activo
A24: =IF(B24="","","P"&TEXT(ROW()-1,"000")) -> P023 | B24: DRAGON L-CARNITINE 32 SERV BLUE RASPBERRY | C24: 1 | D24: 1 | E24: 306 | F24: =IF(OR(E24="",D24="",D24=0),"",E24/D24) -> 306 | G24: 400 | H24: 1 | I24: =IF($B24="","",H24-IF(Ventas!D24="",0,Ventas!D24)) -> 1 | J24: =IF($B24="","",IF(N(I24)=0,"Agotado","Activo")) -> Activo
A25: =IF(B25="","","P"&TEXT(ROW()-1,"000")) -> P024 | B25: ENERGY 16 OZ 12 PK BLUE RASPBERRY "NUEVO SABOR | C25: 1 | D25: 12 | E25: 622 | F25: =IF(OR(E25="",D25="",D25=0),"",E25/D25) -> 51.833333 | G25: 70 | H25: 0 | I25: =IF($B25="","",H25-IF(Ventas!D25="",0,Ventas!D25)) -> 0 | J25: =IF($B25="","",IF(N(I25)=0,"Agotado","Activo")) -> Agotado
A26: =IF(B26="","","P"&TEXT(ROW()-1,"000")) -> P025 | B26: FUEL DRINK 16 OZ/12PACK RING POP CHERRY | C26: 1 | D26: 12 | E26: 591 | F26: =IF(OR(E26="",D26="",D26=0),"",E26/D26) -> 49.25 | G26: 70 | H26: 12 | I26: =IF($B26="","",H26-IF(Ventas!D26="",0,Ventas!D26)) -> 12 | J26: =IF($B26="","",IF(N(I26)=0,"Agotado","Activo")) -> Activo
A27: =IF(B27="","","P"&TEXT(ROW()-1,"000")) -> P026 | B27: GAT SPORT GLUTAMINA 300G | C27: 1 | D27: 1 | E27: 330 | F27: =IF(OR(E27="",D27="",D27=0),"",E27/D27) -> 330 | G27: 400 | H27: 0 | I27: =IF($B27="","",H27-IF(Ventas!D27="",0,Ventas!D27)) -> 0 | J27: =IF($B27="","",IF(N(I27)=0,"Agotado","Activo")) -> Agotado
A28: =IF(B28="","","P"&TEXT(ROW()-1,"000")) -> P027 | B28: GHOST ENERGY 16 OZ 12PK PEACHES | C28: 1 | D28: 12 | E28: 632 | F28: =IF(OR(E28="",D28="",D28=0),"",E28/D28) -> 52.666667 | G28: 70 | H28: 2 | I28: =IF($B28="","",H28-IF(Ventas!D28="",0,Ventas!D28)) -> 2 | J28: =IF($B28="","",IF(N(I28)=0,"Agotado","Activo")) -> Activo
A29: =IF(B29="","","P"&TEXT(ROW()-1,"000")) -> P028 | B29: HTP LIPODRENE AMARILLO 90 TABS | C29: 1 | D29: 1 | E29: 490 | F29: =IF(OR(E29="",D29="",D29=0),"",E29/D29) -> 490 | G29: 550 | H29: 0 | I29: =IF($B29="","",H29-IF(Ventas!D29="",0,Ventas!D29)) -> 0 | J29: =IF($B29="","",IF(N(I29)=0,"Agotado","Activo")) -> Agotado
... A40: =IF(B40="","","P"&TEXT(ROW()-1,"000")) -> P039 | B40: PREENTRENO CBUM ESSENTIAL PWO 30 SERV RED WHITE AND BUM | C40: 1 | D40: 34 | E40: 420 | F40: =IF(OR(E40="",D40="",D40=0),"",E40/D40) -> 12.352941 | G40: 25 | H40: 25 | I40: =IF($B40="","",H40-IF(Ventas!D40="",0,Ventas!D40)) -> 25 | J40: =IF($B40="","",IF(N(I40)=0,"Agotado","Activo")) -> Activo
A41: =IF(B41="","","P"&TEXT(ROW()-1,"000")) -> P040 | B41: PREENTRENO CBUM THAVAGE PWO 40 SERV 6 PEAT | C41: 1 | D41: 43 | E41: 600 | F41: =IF(OR(E41="",D41="",D41=0),"",E41/D41) -> 13.953488 | G41: 25 | H41: 20 | I41: 20 | J41: =IF($B41="","",IF(N(I41)=0,"Agotado","Activo")) -> Activo
A42: =IF(B42="","","P"&TEXT(ROW()-1,"000")) -> P041 | B42: PREENTRENO HYDE NIGHTMARE PWO 30 SERV BLOOD BERRY | C42: 1 | D42: 30 | E42: 420 | F42: =IF(OR(E42="",D42="",D42=0),"",E42/D42) -> 14 | G42: 30 | H42: 30 | I42: =IF($B42="","",H42-IF(Ventas!D42="",0,Ventas!D42)) -> 30 | J42: =IF($B42="","",IF(N(I42)=0,"Agotado","Activo")) -> Activo
A43: =IF(B43="","","P"&TEXT(ROW()-1,"000")) -> P042 | B43: PREENTRENO HYDE NIGHTMARE PWO 30 SERV JAWBREAKER | C43: 1 | D43: 33 | E43: 420 | F43: =IF(OR(E43="",D43="",D43=0),"",E43/D43) -> 12.727273 | G43: 30 | H43: 0 | I43: =IF($B43="","",H43-IF(Ventas!D43="",0,Ventas!D43)) -> 0 | J43: =IF($B43="","",IF(N(I43)=0,"Agotado","Activo")) -> Agotado
A44: =IF(B44="","","P"&TEXT(ROW()-1,"000")) -> P043 | B44: PREENTRENO HYDE NIGHTWARE PWO 30 SERV JAWBREAKER | C44: 1 | D44: 1 | E44: 390 | F44: =IF(OR(E44="",D44="",D44=0),"",E44/D44) -> 390 | G44: 550 | H44: 1 | I44: =IF($B44="","",H44-IF(Ventas!D44="",0,Ventas!D44)) -> 1 | J44: =IF($B44="","",IF(N(I44)=0,"Agotado","Activo")) -> Activo
A45: =IF(B45="","","P"&TEXT(ROW()-1,"000")) -> P044 | B45: PREENTRENO PANDA | C45: 1 | D45: 1 | E45: 490 | F45: =IF(OR(E45="",D45="",D45=0),"",E45/D45) -> 490 | G45: 600 | H45: 1 | I45: =IF($B45="","",H45-IF(Ventas!D45="",0,Ventas!D45)) -> 1 | J45: =IF($B45="","",IF(N(I45)=0,"Agotado","Activo")) -> Activo
A46: =IF(B46="","","P"&TEXT(ROW()-1,"000")) -> P045 | B46: PREENTRENO PANDA FIRST BLOOD PWO 20 SERV SOUR BLUE RASPBERRY | C46: 1 | D46: 25 | E46: 700 | F46: =IF(OR(E46="",D46="",D46=0),"",E46/D46) -> 28 | G46: =IF(F46="","",ROUND(F46*1.33,0)) -> 37 | H46: 50 | I46: 25 | J46: =IF($B46="","",IF(N(I46)=0,"Agotado","Activo")) -> Activo
A47: =IF(B47="","","P"&TEXT(ROW()-1,"000")) -> P046 | B47: PREENTRENO RYSE LOADED PRE 30 SERV KOOL AID TROPICAL PUNCH | C47: 1 | D47: 30 | E47: 500 | F47: =IF(OR(E47="",D47="",D47=0),"",E47/D47) -> 16.666667 | G47: 25 | H47: 13 | I47: =IF($B47="","",H47-IF(Ventas!D47="",0,Ventas!D47)) -> 13 | J47: =IF($B47="","",IF(N(I47)=0,"Agotado","Activo")) -> Activo
A48: =IF(B48="","","P"&TEXT(ROW()-1,"000")) -> P047 | B48: PREENTRENO VENOM | C48: 1 | D48: 1 | E48: 520 | F48: =IF(OR(E48="",D48="",D48=0),"",E48/D48) -> 520 | G48: 600 | H48: 0 | I48: =IF($B48="","",H48-IF(Ventas!D48="",0,Ventas!D48)) -> 0 | J48: =IF($B48="","",IF(N(I48)=0,"Agotado","Activo")) -> Agotado
A49: =IF(B49="","","P"&TEXT(ROW()-1,"000")) -> P048 | B49: PREENTRENO VENOM (unidad) | C49: 1 | D49: 27 | E49: 520 | F49: =IF(OR(E49="",D49="",D49=0),"",E49/D49) -> 19.259259 | G49: 40 | H49: 17 | I49: =IF($B49="","",H49-IF(Ventas!D49="",0,Ventas!D49)) -> 17 | J49: =IF($B49="","",IF(N(I49)=0,"Agotado","Activo")) -> Activo
A50: =IF(B50="","","P"&TEXT(ROW()-1,"000")) -> P049 | B50: PREETRENO RYSE GODZILLA BACK BERRY LEMONADE | C50: 1 | D50: 30 | E50: 629 | F50: =IF(OR(E50="",D50="",D50=0),"",E50/D50) -> 20.966667 | G50: 40 | H50: 0 | I50: =IF($B50="","",H50-IF(Ventas!D50="",0,Ventas!D50)) -> 0 | J50: =IF($B50="","",IF(N(I50)=0,"Agotado","Activo")) -> Agotado
A51: =IF(B51="","","P"&TEXT(ROW()-1,"000")) -> P050 | B51: PREETRENO RYSE GODZILLA BACK BERRY LEMONADE | C51: 1 | D51: 1 | E51: 650 | F51: =IF(OR(E51="",D51="",D51=0),"",E51/D51) -> 650 | G51: 750 | H51: 1 | I51: =IF($B51="","",H51-IF(Ventas!D51="",0,Ventas!D51)) -> 1 | J51: =IF($B51="","",IF(N(I51)=0,"Agotado","Activo")) -> Activo
A52: =IF(B52="","","P"&TEXT(ROW()-1,"000")) -> P051 | B52: PROTEIN BAR 12 PCK DOUBLE FUDGE BROWNIE | C52: 1 | D52: 12 | E52: 526 | F52: =IF(OR(E52="",D52="",D52=0),"",E52/D52) -> 43.833333 | G52: 60 | H52: 13 | I52: =IF($B52="","",H52-IF(Ventas!D52="",0,Ventas!D52)) -> 13 | J52: =IF($B52="","",IF(N(I52)=0,"Agotado","Activo")) -> Activo
A53: =IF(B53="","","P"&TEXT(ROW()-1,"000")) -> P052 | B53: PROTEINA BAR 12PACK DOUBLE FUDGE BRWNIE | C53: 1 | D53: 12 | E53: 560 | F53: =IF(OR(E53="",D53="",D53=0),"",E53/D53) -> 46.666667 | G53: 60 | H53: 12 | I53: =IF($B53="","",H53-IF(Ventas!D53="",0,Ventas!D53)) -> 12 | J53: =IF($B53="","",IF(N(I53)=0,"Agotado","Activo")) -> Activo
A54: =IF(B54="","","P"&TEXT(ROW()-1,"000")) -> P053 | B54: PROTEINA ISIPHORM 5 LBS VAINILLA | C54: 1 | D54: 1 | E54: 1590 | F54: =IF(OR(E54="",D54="",D54=0),"",E54/D54) -> 1590 | G54: 1750 | H54: 1 | I54: =IF($B54="","",H54-IF(Ventas!D54="",0,Ventas!D54)) -> 1 | J54: =IF($B54="","",IF(N(I54)=0,"Agotado","Activo")) -> Activo
A55: =IF(B55="","","P"&TEXT(ROW()-1,"000")) -> P054 | B55: PROTEINA ISO HD 5 LBS COOKIES BUTTER | C55: 1 | D55: 1 | E55: 1029 | F55: =IF(OR(E55="",D55="",D55=0),"",E55/D55) -> 1029 | G55: 1300 | H55: 0 | I55: =IF($B55="","",H55-IF(Ventas!D55="",0,Ventas!D55)) -> 0 | J55: =IF($B55="","",IF(N(I55)=0,"Agotado","Activo")) -> Agotado
A56: =IF(B56="","","P"&TEXT(ROW()-1,"000")) -> P055 | B56: PROTEINA ISO-HD 5 LBS COOKIES BUTTER | C56: 1 | D56: 70 | E56: 1100 | F56: =IF(OR(E56="",D56="",D56=0),"",E56/D56) -> 15.714286 | G56: 35 | H56: 60 | I56: =IF($B56="","",H56-IF(Ventas!D56="",0,Ventas!D56)) -> 50 | J56: =IF($B56="","",IF(N(I56)=0,"Agotado","Activo")) -> Activo
A57: =IF(B57="","","P"&TEXT(ROW()-1,"000")) -> P056 | B57: PROTEINA ISOFIT 5 LBS STRAWBERRY AND CREAM | C57: 1 | D57: 1 | E57: 1200 | F57: =IF(OR(E57="",D57="",D57=0),"",E57/D57) -> 1200 | G57: 1400 | H57: 1 | I57: =IF($B57="","",H57-IF(Ventas!D57="",0,Ventas!D57)) -> 1 | J57: =IF($B57="","",IF(N(I57)=0,"Agotado","Activo")) -> Activo
A58: =IF(B58="","","P"&TEXT(ROW()-1,"000")) -> P057 | B58: PROTEINA ISOPHORM 5 LBS BLUEBERR ICE CREAM | C58: 1 | D58: 1 | E58: 1600 | F58: =IF(OR(E58="",D58="",D58=0),"",E58/D58) -> 1600 | G58: 1750 | H58: 1 | I58: =IF($B58="","",H58-IF(Ventas!D58="",0,Ventas!D58)) -> 1 | J58: =IF($B58="","",IF(N(I58)=0,"Agotado","Activo")) -> Activo
... A63: =IF(B63="","","P"&TEXT(ROW()-1,"000")) -> P062 | B63: RAW CREATINE MONOHYDRATE 250 SERV UNFLAVORED *NUEVO* | C63: 1 | D63: 1 | E63: 640 | F63: =IF(OR(E63="",D63="",D63=0),"",E63/D63) -> 640 | G63: 780 | H63: 0 | I63: =IF($B63="","",H63-IF(Ventas!D63="",0,Ventas!D63)) -> 0 | J63: =IF($B63="","",IF(N(I63)=0,"Agotado","Activo")) -> Agotado
A64: =IF(B64="","","P"&TEXT(ROW()-1,"000")) -> P063 | B64: RAW MY COOKIE DEALER 113 G 12 PACK MILK & COOKIES | C64: 1 | D64: 12 | E64: 600 | F64: =IF(OR(E64="",D64="",D64=0),"",E64/D64) -> 50 | G64: 70 | H64: 22 | I64: 22 | J64: =IF($B64="","",IF(N(I64)=0,"Agotado","Activo")) -> Activo
A65: =IF(B65="","","P"&TEXT(ROW()-1,"000")) -> P064 | B65: TESTROL GOGA TESTROL GOLD 60 TABSLD | C65: 1 | D65: 1 | E65: 275 | F65: =IF(OR(E65="",D65="",D65=0),"",E65/D65) -> 275 | G65: 480 | H65: 1 | I65: =IF($B65="","",H65-IF(Ventas!D65="",0,Ventas!D65)) -> 1 | J65: =IF($B65="","",IF(N(I65)=0,"Agotado","Activo")) -> Activo
A66: =IF(B66="","","P"&TEXT(ROW()-1,"000")) -> P065 | B66: THINK HIGH PROTEIN 10 BARS CHUNKY PEANUT BUTTER | C66: 1 | D66: 10 | E66: 400 | F66: =IF(OR(E66="",D66="",D66=0),"",E66/D66) -> 40 | G66: 50 | H66: 0 | I66: =IF($B66="","",H66-IF(Ventas!D66="",0,Ventas!D66)) -> 0 | J66: =IF($B66="","",IF(N(I66)=0,"Agotado","Activo")) -> Agotado
A67: =IF(B67="","","P"&TEXT(ROW()-1,"000")) -> P066 | B67: THINK HIGH PROTEIN 10 BARS COOKIES & CREAM | C67: 1 | D67: 10 | E67: 400 | F67: =IF(OR(E67="",D67="",D67=0),"",E67/D67) -> 40 | G67: 50 | H67: 0 | I67: =IF($B67="","",H67-IF(Ventas!D67="",0,Ventas!D67)) -> 0 | J67: =IF($B67="","",IF(N(I67)=0,"Agotado","Activo")) -> Agotado
A68: =IF(B68="","","P"&TEXT(ROW()-1,"000")) -> P067 | B68: TOTAL WAR BLACK OPS 20 SERV TIGERS BLOOD *CAD 07/27* | C68: 1 | D68: 25 | E68: 550 | F68: =IF(OR(E68="",D68="",D68=0),"",E68/D68) -> 22 | G68: 40 | H68: 25 | I68: =IF($B68="","",H68-IF(Ventas!D68="",0,Ventas!D68)) -> 25 | J68: =IF($B68="","",IF(N(I68)=0,"Agotado","Activo")) -> Activo
A69: =IF(B69="","","P"&TEXT(ROW()-1,"000")) -> P068 | B69: VASOS SHAKERS | C69: 1 | D69: 3 | E69: 300 | F69: =IF(OR(E69="",D69="",D69=0),"",E69/D69) -> 100 | G69: 130 | H69: 3 | I69: =IF($B69="","",H69-IF(Ventas!D69="",0,Ventas!D69)) -> 1 | J69: =IF($B69="","",IF(N(I69)=0,"Agotado","Activo")) -> Activo
A70: =IF(B70="","","P"&TEXT(ROW()-1,"000")) | C70: 1 | D70: 27 | E70: 490 | F70: =IF(OR(E70="",D70="",D70=0),"",E70/D70) -> 18.148148 | G70: 40 | I70: =IF($B70="","",H70-IF(Ventas!D70="",0,Ventas!D70)) | J70: =IF($B70="","",IF(N(I70)=0,"Agotado","Activo"))
A71: =IF(B71="","","P"&TEXT(ROW()-1,"000")) | F71: =IF(OR(E71="",D71="",D71=0),"",E71/D71) | G71: =IF(F71="","",ROUND(F71*1.33,0)) | I71: =IF($B71="","",H71-IF(Ventas!D71="",0,Ventas!D71)) | J71: =IF($B71="","",IF(N(I71)=0,"Agotado","Activo"))
A72: =IF(B72="","","P"&TEXT(ROW()-1,"000")) | F72: =IF(OR(E72="",D72="",D72=0),"",E72/D72) | G72: =IF(F72="","",ROUND(F72*1.33,0)) | I72: =IF($B72="","",H72-IF(Ventas!D72="",0,Ventas!D72)) | J72: =IF($B72="","",IF(N(I72)=0,"Agotado","Activo"))
A73: =IF(B73="","","P"&TEXT(ROW()-1,"000")) | F73: =IF(OR(E73="",D73="",D73=0),"",E73/D73) | G73: =IF(F73="","",ROUND(F73*1.33,0)) | I73: =IF($B73="","",H73-IF(Ventas!D73="",0,Ventas!D73)) | J73: =IF($B73="","",IF(N(I73)=0,"Agotado","Activo"))
A74: =IF(B74="","","P"&TEXT(ROW()-1,"000")) | F74: =IF(OR(E74="",D74="",D74=0),"",E74/D74) | G74: =IF(F74="","",ROUND(F74*1.33,0)) | I74: =IF($B74="","",H74-IF(Ventas!D74="",0,Ventas!D74)) | J74: =IF($B74="","",IF(N(I74)=0,"Agotado","Activo"))
A75: =IF(B75="","","P"&TEXT(ROW()-1,"000")) | F75: =IF(OR(E75="",D75="",D75=0),"",E75/D75) | G75: =IF(F75="","",ROUND(F75*1.33,0)) | I75: =IF($B75="","",H75-IF(Ventas!D75="",0,Ventas!D75)) | J75: =IF($B75="","",IF(N(I75)=0,"Agotado","Activo"))
A76: =IF(B76="","","P"&TEXT(ROW()-1,"000")) | F76: =IF(OR(E76="",D76="",D76=0),"",E76/D76) | G76: =IF(F76="","",ROUND(F76*1.33,0)) | I76: =IF($B76="","",H76-IF(Ventas!D76="",0,Ventas!D76)) | J76: =IF($B76="","",IF(N(I76)=0,"Agotado","Activo"))
A77: =IF(B77="","","P"&TEXT(ROW()-1,"000")) | F77: =IF(OR(E77="",D77="",D77=0),"",E77/D77) | G77: =IF(F77="","",ROUND(F77*1.33,0)) | I77: =IF($B77="","",H77-IF(Ventas!D77="",0,Ventas!D77)) | J77: =IF($B77="","",IF(N(I77)=0,"Agotado","Activo"))
A78: =IF(B78="","","P"&TEXT(ROW()-1,"000")) | F78: =IF(OR(E78="",D78="",D78=0),"",E78/D78) | G78: =IF(F78="","",ROUND(F78*1.33,0)) | I78: =IF($B78="","",H78-IF(Ventas!D78="",0,Ventas!D78)) | J78: =IF($B78="","",IF(N(I78)=0,"Agotado","Activo"))
A79: =IF(B79="","","P"&TEXT(ROW()-1,"000")) | F79: =IF(OR(E79="",D79="",D79=0),"",E79/D79) | G79: =IF(F79="","",ROUND(F79*1.33,0)) | I79: =IF($B79="","",H79-IF(Ventas!D79="",0,Ventas!D79)) | J79: =IF($B79="","",IF(N(I79)=0,"Agotado","Activo"))
A80: =IF(B80="","","P"&TEXT(ROW()-1,"000")) | F80: =IF(OR(E80="",D80="",D80=0),"",E80/D80) | G80: =IF(F80="","",ROUND(F80*1.33,0)) | I80: =IF($B80="","",H80-IF(Ventas!D80="",0,Ventas!D80)) | J80: =IF($B80="","",IF(N(I80)=0,"Agotado","Activo"))
A81: =IF(B81="","","P"&TEXT(ROW()-1,"000")) | F81: =IF(OR(E81="",D81="",D81=0),"",E81/D81) | G81: =IF(F81="","",ROUND(F81*1.33,0)) | I81: =IF($B81="","",H81-IF(Ventas!D81="",0,Ventas!D81)) | J81: =IF($B81="","",IF(N(I81)=0,"Agotado","Activo"))
A82: =IF(B82="","","P"&TEXT(ROW()-1,"000")) | F82: =IF(OR(E82="",D82="",D82=0),"",E82/D82) | G82: =IF(F82="","",ROUND(F82*1.33,0)) | I82: =IF($B82="","",H82-IF(Ventas!D82="",0,Ventas!D82)) | J82: =IF($B82="","",IF(N(I82)=0,"Agotado","Activo"))
... A1000: =IF(B1000="","","P"&TEXT(ROW()-1,"000")) | F1000: =IF(OR(E1000="",D1000="",D1000=0),"",E1000/D1000) | G1000: =IF(F1000="","",ROUND(F1000*1.33,0)) | I1000: =IF($B1000="","",H1000-IF(Ventas!D1000="",0,Ventas!D1000)) | J1000: =IF($B1000="","",IF(N(I1000)=0,"Agotado","Activo"))

Sheet Ventas
A1: ID | B1: Producto | C1: Stock inicial | D1: Piezas vendidas | E1: Stock actual | F1: Total vendido | G1: Dinero para resurtir | H1: Ganancia pura | I1: Estado | K1: PRODUCTOS VENDIDOS
A2: =IF(Productos!A2="","",Productos!A2) -> P001 | B2: =IF(Productos!B2="","",Productos!B2) -> AN ABE ENERGY DRINK 11.2 OZ 12PK TANG ORANGE | C2: =IF(Productos!$A2="","",Productos!H2) -> 0 | E2: =IF(C2="","",C2-IF(D2="",0,D2)) -> 0 | F2: =IF(A2="","",IF(D2="",0,D2*Productos!G2)) -> 0 | G2: =IF(A2="","",IF(D2="",0,D2*Productos!F2)) -> 0 | H2: =IF(A2="","",F2-G2) -> 0 | I2: =IF(A2="","",Productos!J2) -> Agotado | K2: Producto | L2: Piezas vendidas | M2: Costo del producto | N2: Dinero para resurtir | O2: Ganancia
A3: =IF(Productos!A3="","",Productos!A3) -> P002 | B3: =IF(Productos!B3="","",Productos!B3) -> ARMADA ASHWAGANDHA + L-TEANINA 600 MG 90 CAPS | C3: =IF(Productos!$A3="","",Productos!H3) -> 1 | E3: =IF(C3="","",C3-IF(D3="",0,D3)) -> 1 | F3: =IF(A3="","",IF(D3="",0,D3*Productos!G3)) -> 0 | G3: =IF(A3="","",IF(D3="",0,D3*Productos!F3)) -> 0 | H3: =IF(A3="","",F3-G3) -> 0 | I3: =IF(A3="","",Productos!J3) -> Activo | K3: {=IFERROR(_xlfn._xlws.FILTER(_xlfn.HSTACK(B2:B1000,D2:D1000,Productos!E2:E1000,G2:G1000,H2:H1000),(D2:D1000<>"")*(D2:D1000>0),"Sin ventas registradas"),"Sin ventas registradas")} -> BEBIDA CELSIUS | L3: 2 | M3: 600 | N3: 100 | O3: 40
A4: =IF(Productos!A4="","",Productos!A4) -> P003 | B4: =IF(Productos!B4="","",Productos!B4) -> ARMADA CITRATO DE MAGNESIO 1000 MG 100 CAPS | C4: =IF(Productos!$A4="","",Productos!H4) -> 1 | E4: =IF(C4="","",C4-IF(D4="",0,D4)) -> 1 | F4: =IF(A4="","",IF(D4="",0,D4*Productos!G4)) -> 0 | G4: =IF(A4="","",IF(D4="",0,D4*Productos!F4)) -> 0 | H4: =IF(A4="","",F4-G4) -> 0 | I4: =IF(A4="","",Productos!J4) -> Activo | K4: BLOOM SURTIDO | L4: 10 | M4: 550 | N4: 458.33333 | O4: 191.66667
A5: =IF(Productos!A5="","",Productos!A5) -> P004 | B5: =IF(Productos!B5="","",Productos!B5) -> BEBIDA CELSIUS | C5: =IF(Productos!$A5="","",Productos!H5) -> 14 | D5: 2 | E5: =IF(C5="","",C5-IF(D5="",0,D5)) -> 12 | F5: =IF(A5="","",IF(D5="",0,D5*Productos!G5)) -> 140 | G5: =IF(A5="","",IF(D5="",0,D5*Productos!F5)) -> 100 | H5: =IF(A5="","",F5-G5) -> 40 | I5: =IF(A5="","",Productos!J5) -> Activo | K5: BSN PROTEIN CRIPS 12 BARS VANILLA MARSHMALLOW *OFERTA* | L5: 12 | M5: 600 | N5: 600 | O5: 180
A6: =IF(Productos!A6="","",Productos!A6) -> P005 | B6: =IF(Productos!B6="","",Productos!B6) -> BLOOM 25 SERV PAQUETE | C6: =IF(Productos!$A6="","",Productos!H6) -> 1 | E6: =IF(C6="","",C6-IF(D6="",0,D6)) -> 1 | F6: =IF(A6="","",IF(D6="",0,D6*Productos!G6)) -> 0 | G6: =IF(A6="","",IF(D6="",0,D6*Productos!F6)) -> 0 | H6: =IF(A6="","",F6-G6) -> 0 | I6: =IF(A6="","",Productos!J6) -> Activo | K6: CREATINA BIRDMAN | L6: 3 | M6: 780 | N6: 1170 | O6: 120
A7: =IF(Productos!A7="","",Productos!A7) -> P006 | B7: =IF(Productos!B7="","",Productos!B7) -> BLOOM SPAERKALING ENERGY 12OZ PEACH WATERMELON | C7: =IF(Productos!$A7="","",Productos!H7) -> 0 | E7: =IF(C7="","",C7-IF(D7="",0,D7)) -> 0 | F7: =IF(A7="","",IF(D7="",0,D7*Productos!G7)) -> 0 | G7: =IF(A7="","",IF(D7="",0,D7*Productos!F7)) -> 0 | H7: =IF(A7="","",F7-G7) -> 0 | I7: =IF(A7="","",Productos!J7) -> Agotado | K7: CREATINA BIRDMAN CON ELECTROLIT | L7: 1 | M7: 350 | N7: 350 | O7: 80
A8: =IF(Productos!A8="","",Productos!A8) -> P007 | B8: =IF(Productos!B8="","",Productos!B8) -> BLOOM SPARKLING ENERGY 12OZ PEACH MANGO | C8: =IF(Productos!$A8="","",Productos!H8) -> 0 | E8: =IF(C8="","",C8-IF(D8="",0,D8)) -> 0 | F8: =IF(A8="","",IF(D8="",0,D8*Productos!G8)) -> 0 | G8: =IF(A8="","",IF(D8="",0,D8*Productos!F8)) -> 0 | H8: =IF(A8="","",F8-G8) -> 0 | I8: =IF(A8="","",Productos!J8) -> Agotado | K8: OUTLET ISOFLEX 5LB CHOCOLATE PEANUT BUTTER | L8: 10 | M8: 1120 | N8: 160 | O8: 190
A9: =IF(Productos!A9="","",Productos!A9) -> P008 | B9: =IF(Productos!B9="","",Productos!B9) -> BLOOM SPEARKLING ENERGY 12OZ PEACH LEMONS | C9: =IF(Productos!$A9="","",Productos!H9) -> 0 | E9: =IF(C9="","",C9-IF(D9="",0,D9)) -> 0 | F9: =IF(A9="","",IF(D9="",0,D9*Productos!G9)) -> 0 | G9: =IF(A9="","",IF(D9="",0,D9*Productos!F9)) -> 0 | H9: =IF(A9="","",F9-G9) -> 0 | I9: =IF(A9="","",Productos!J9) -> Agotado | K9: PREENTRENO CBUM THAVAGE PWO 40 SERV 6 PEAT | L9: 20 | M9: 600 | N9: 279.06977 | O9: 220.93023
A10: =IF(Productos!A10="","",Productos!A10) -> P009 | B10: =IF(Productos!B10="","",Productos!B10) -> BLOOM SURTIDO | C10: =IF(Productos!$A10="","",Productos!H10) -> 11 | D10: 10 | E10: =IF(C10="","",C10-IF(D10="",0,D10)) -> 1 | F10: =IF(A10="","",IF(D10="",0,D10*Productos!G10)) -> 650 | G10: =IF(A10="","",IF(D10="",0,D10*Productos!F10)) -> 458.33333 | H10: =IF(A10="","",F10-G10) -> 191.66667 | I10: =IF(A10="","",Productos!J10) -> Activo | K10: PROTEINA ISO-HD 5 LBS COOKIES BUTTER | L10: 10 | M10: 1100 | N10: 157.14286 | O10: 192.85714
A11: =IF(Productos!A11="","",Productos!A11) -> P010 | B11: =IF(Productos!B11="","",Productos!B11) -> BSN NO-XPLODE VASO PUMP 24 SERV PINEAPPLE PUMP | C11: =IF(Productos!$A11="","",Productos!H11) -> 1 | E11: =IF(C11="","",C11-IF(D11="",0,D11)) -> 1 | F11: =IF(A11="","",IF(D11="",0,D11*Productos!G11)) -> 0 | G11: =IF(A11="","",IF(D11="",0,D11*Productos!F11)) -> 0 | H11: =IF(A11="","",F11-G11) -> 0 | I11: =IF(A11="","",Productos!J11) -> Activo | K11: PROTEINA ISOPURE ZERO CARB 4.5 LBS VAINILLA | L11: 1 | M11: 1500 | N11: 1500 | O11: 200
A12: =IF(Productos!A12="","",Productos!A12) -> P011 | B12: =IF(Productos!B12="","",Productos!B12) -> BSN PROTEIN CRIPS 12 BARS VANILLA MARSHMALLOW *OFERTA* | C12: =IF(Productos!$A12="","",Productos!H12) -> 12 | D12: 12 | E12: =IF(C12="","",C12-IF(D12="",0,D12)) -> 0 | F12: =IF(A12="","",IF(D12="",0,D12*Productos!G12)) -> 780 | G12: =IF(A12="","",IF(D12="",0,D12*Productos!F12)) -> 600 | H12: =IF(A12="","",F12-G12) -> 180 | I12: =IF(A12="","",Productos!J12) -> Agotado | K12: PROTEINA RAW CBUM ITHOLATE 5 LBS COOKIES & CREAM (UND) | L12: 10 | M12: 1400 | N12: 200 | O12: 150
A13: =IF(Productos!A13="","",Productos!A13) -> P012 | B13: =IF(Productos!B13="","",Productos!B13) -> CBUM ESSENTIAL PWO 30 SERV BLUE RASPBERRY | C13: =IF(Productos!$A13="","",Productos!H13) -> 0 | E13: =IF(C13="","",C13-IF(D13="",0,D13)) -> 0 | F13: =IF(A13="","",IF(D13="",0,D13*Productos!G13)) -> 0 | G13: =IF(A13="","",IF(D13="",0,D13*Productos!F13)) -> 0 | H13: =IF(A13="","",F13-G13) -> 0 | I13: =IF(A13="","",Productos!J13) -> Agotado | K13: RAW CBUM ESSENTIAL PWO 30 SERV JAMAICA *EDICION LIMITADA* | L13: 20 | M13: 420 | N13: 254.54545 | O13: 245.45455
A14: =IF(Productos!A14="","",Productos!A14) -> P013 | B14: =IF(Productos!B14="","",Productos!B14) -> CBUM ESSENTIAL PWO 30 SERV GUAVA | C14: =IF(Productos!$A14="","",Productos!H14) -> 0 | E14: =IF(C14="","",C14-IF(D14="",0,D14)) -> 0 | F14: =IF(A14="","",IF(D14="",0,D14*Productos!G14)) -> 0 | G14: =IF(A14="","",IF(D14="",0,D14*Productos!F14)) -> 0 | H14: =IF(A14="","",F14-G14) -> 0 | I14: =IF(A14="","",Productos!J14) -> Agotado | K14: RAW MY COOKIE DEALER 113 G 12 PACK MILK & COOKIES | L14: 22 | M14: 600 | N14: 1100 | O14: 440
A15: =IF(Productos!A15="","",Productos!A15) -> P014 | B15: =IF(Productos!B15="","",Productos!B15) -> CBUM ESSENTIAL PWO 30 SERV LYCHEE | C15: =IF(Productos!$A15="","",Productos!H15) -> 0 | E15: =IF(C15="","",C15-IF(D15="",0,D15)) -> 0 | F15: =IF(A15="","",IF(D15="",0,D15*Productos!G15)) -> 0 | G15: =IF(A15="","",IF(D15="",0,D15*Productos!F15)) -> 0 | H15: =IF(A15="","",F15-G15) -> 0 | I15: =IF(A15="","",Productos!J15) -> Agotado | K15: VASOS SHAKERS | L15: 2 | M15: 300 | N15: 200 | O15: 60
A16: =IF(Productos!A16="","",Productos!A16) -> P015 | B16: =IF(Productos!B16="","",Productos!B16) -> CBUM ESSENTIAL PWO 30SER GUAVA FRUIT | C16: =IF(Productos!$A16="","",Productos!H16) -> 0 | E16: =IF(C16="","",C16-IF(D16="",0,D16)) -> 0 | F16: =IF(A16="","",IF(D16="",0,D16*Productos!G16)) -> 0 | G16: =IF(A16="","",IF(D16="",0,D16*Productos!F16)) -> 0 | H16: =IF(A16="","",F16-G16) -> 0 | I16: =IF(A16="","",Productos!J16) -> Agotado
A17: =IF(Productos!A17="","",Productos!A17) -> P016 | B17: =IF(Productos!B17="","",Productos!B17) -> CREATINA BIRDMAN | C17: =IF(Productos!$A17="","",Productos!H17) -> 3 | D17: 3 | E17: =IF(C17="","",C17-IF(D17="",0,D17)) -> 0 | F17: =IF(A17="","",IF(D17="",0,D17*Productos!G17)) -> 1290 | G17: =IF(A17="","",IF(D17="",0,D17*Productos!F17)) -> 1170 | H17: =IF(A17="","",F17-G17) -> 120 | I17: =IF(A17="","",Productos!J17) -> Activo
A18: =IF(Productos!A18="","",Productos!A18) -> P017 | B18: =IF(Productos!B18="","",Productos!B18) -> CREATINA BIRDMAN CON ELECTROLIT | C18: =IF(Productos!$A18="","",Productos!H18) -> 2 | D18: 1 | E18: =IF(C18="","",C18-IF(D18="",0,D18)) -> 1 | F18: =IF(A18="","",IF(D18="",0,D18*Productos!G18)) -> 430 | G18: =IF(A18="","",IF(D18="",0,D18*Productos!F18)) -> 350 | H18: =IF(A18="","",F18-G18) -> 80 | I18: =IF(A18="","",Productos!J18) -> Activo
A19: =IF(Productos!A19="","",Productos!A19) -> P018 | B19: =IF(Productos!B19="","",Productos!B19) -> CREATINA DRAGON PHARMA MONOHYDRATE 1KG | C19: =IF(Productos!$A19="","",Productos!H19) -> 2 | E19: =IF(C19="","",C19-IF(D19="",0,D19)) -> 2 | F19: =IF(A19="","",IF(D19="",0,D19*Productos!G19)) -> 0 | G19: =IF(A19="","",IF(D19="",0,D19*Productos!F19)) -> 0 | H19: =IF(A19="","",F19-G19) -> 0 | I19: =IF(A19="","",Productos!J19) -> Activo
A20: =IF(Productos!A20="","",Productos!A20) -> P019 | B20: =IF(Productos!B20="","",Productos!B20) -> CREATINA DRAGON PHARMACREATINE MONOHYDRATE 300 GRS UNFLAVORED | C20: =IF(Productos!$A20="","",Productos!H20) -> 0 | E20: =IF(C20="","",C20-IF(D20="",0,D20)) -> 0 | F20: =IF(A20="","",IF(D20="",0,D20*Productos!G20)) -> 0 | G20: =IF(A20="","",IF(D20="",0,D20*Productos!F20)) -> 0 | H20: =IF(A20="","",F20-G20) -> 0 | I20: =IF(A20="","",Productos!J20) -> Agotado
A21: =IF(Productos!A21="","",Productos!A21) -> P020 | B21: =IF(Productos!B21="","",Productos!B21) -> CREATINA MONOHIDRATADA CAT 300GR | C21: =IF(Productos!$A21="","",Productos!H21) -> 1 | E21: =IF(C21="","",C21-IF(D21="",0,D21)) -> 1 | F21: =IF(A21="","",IF(D21="",0,D21*Productos!G21)) -> 0 | G21: =IF(A21="","",IF(D21="",0,D21*Productos!F21)) -> 0 | H21: =IF(A21="","",F21-G21) -> 0 | I21: =IF(A21="","",Productos!J21) -> Activo
A22: =IF(Productos!A22="","",Productos!A22) -> P021 | B22: =IF(Productos!B22="","",Productos!B22) -> CREATINA MONOHYDRATADA CAT 1000GR | C22: =IF(Productos!$A22="","",Productos!H22) -> 2 | E22: =IF(C22="","",C22-IF(D22="",0,D22)) -> 2 | F22: =IF(A22="","",IF(D22="",0,D22*Productos!G22)) -> 0 | G22: =IF(A22="","",IF(D22="",0,D22*Productos!F22)) -> 0 | H22: =IF(A22="","",F22-G22) -> 0 | I22: =IF(A22="","",Productos!J22) -> Activo
A23: =IF(Productos!A23="","",Productos!A23) -> P022 | B23: =IF(Productos!B23="","",Productos!B23) -> DIPS DRAGON PHARMA | C23: =IF(Productos!$A23="","",Productos!H23) -> 4 | E23: =IF(C23="","",C23-IF(D23="",0,D23)) -> 4 | F23: =IF(A23="","",IF(D23="",0,D23*Productos!G23)) -> 0 | G23: =IF(A23="","",IF(D23="",0,D23*Productos!F23)) -> 0 | H23: =IF(A23="","",F23-G23) -> 0 | I23: =IF(A23="","",Productos!J23) -> Activo
A24: =IF(Productos!A24="","",Productos!A24) -> P023 | B24: =IF(Productos!B24="","",Productos!B24) -> DRAGON L-CARNITINE 32 SERV BLUE RASPBERRY | C24: =IF(Productos!$A24="","",Productos!H24) -> 1 | E24: =IF(C24="","",C24-IF(D24="",0,D24)) -> 1 | F24: =IF(A24="","",IF(D24="",0,D24*Productos!G24)) -> 0 | G24: =IF(A24="","",IF(D24="",0,D24*Productos!F24)) -> 0 | H24: =IF(A24="","",F24-G24) -> 0 | I24: =IF(A24="","",Productos!J24) -> Activo
A25: =IF(Productos!A25="","",Productos!A25) -> P024 | B25: =IF(Productos!B25="","",Productos!B25) -> ENERGY 16 OZ 12 PK BLUE RASPBERRY "NUEVO SABOR | C25: =IF(Productos!$A25="","",Productos!H25) -> 0 | E25: =IF(C25="","",C25-IF(D25="",0,D25)) -> 0 | F25: =IF(A25="","",IF(D25="",0,D25*Productos!G25)) -> 0 | G25: =IF(A25="","",IF(D25="",0,D25*Productos!F25)) -> 0 | H25: =IF(A25="","",F25-G25) -> 0 | I25: =IF(A25="","",Productos!J25) -> Agotado
A26: =IF(Productos!A26="","",Productos!A26) -> P025 | B26: =IF(Productos!B26="","",Productos!B26) -> FUEL DRINK 16 OZ/12PACK RING POP CHERRY | C26: =IF(Productos!$A26="","",Productos!H26) -> 12 | E26: =IF(C26="","",C26-IF(D26="",0,D26)) -> 12 | F26: =IF(A26="","",IF(D26="",0,D26*Productos!G26)) -> 0 | G26: =IF(A26="","",IF(D26="",0,D26*Productos!F26)) -> 0 | H26: =IF(A26="","",F26-G26) -> 0 | I26: =IF(A26="","",Productos!J26) -> Activo
A27: =IF(Productos!A27="","",Productos!A27) -> P026 | B27: =IF(Productos!B27="","",Productos!B27) -> GAT SPORT GLUTAMINA 300G | C27: =IF(Productos!$A27="","",Productos!H27) -> 0 | E27: =IF(C27="","",C27-IF(D27="",0,D27)) -> 0 | F27: =IF(A27="","",IF(D27="",0,D27*Productos!G27)) -> 0 | G27: =IF(A27="","",IF(D27="",0,D27*Productos!F27)) -> 0 | H27: =IF(A27="","",F27-G27) -> 0 | I27: =IF(A27="","",Productos!J27) -> Agotado
A28: =IF(Productos!A28="","",Productos!A28) -> P027 | B28: =IF(Productos!B28="","",Productos!B28) -> GHOST ENERGY 16 OZ 12PK PEACHES | C28: =IF(Productos!$A28="","",Productos!H28) -> 2 | E28: =IF(C28="","",C28-IF(D28="",0,D28)) -> 2 | F28: =IF(A28="","",IF(D28="",0,D28*Productos!G28)) -> 0 | G28: =IF(A28="","",IF(D28="",0,D28*Productos!F28)) -> 0 | H28: =IF(A28="","",F28-G28) -> 0 | I28: =IF(A28="","",Productos!J28) -> Activo
A29: =IF(Productos!A29="","",Productos!A29) -> P028 | B29: =IF(Productos!B29="","",Productos!B29) -> HTP LIPODRENE AMARILLO 90 TABS | C29: =IF(Productos!$A29="","",Productos!H29) -> 0 | E29: =IF(C29="","",C29-IF(D29="",0,D29)) -> 0 | F29: =IF(A29="","",IF(D29="",0,D29*Productos!G29)) -> 0 | G29: =IF(A29="","",IF(D29="",0,D29*Productos!F29)) -> 0 | H29: =IF(A29="","",F29-G29) -> 0 | I29: =IF(A29="","",Productos!J29) -> Agotado
A30: =IF(Productos!A30="","",Productos!A30) -> P029 | B30: =IF(Productos!B30="","",Productos!B30) -> ISO 100 1.3 LBS 20 SERV DUNKIN CAPPUCCIONO | C30: =IF(Productos!$A30="","",Productos!H30) -> 0 | E30: =IF(C30="","",C30-IF(D30="",0,D30)) -> 0 | F30: =IF(A30="","",IF(D30="",0,D30*Productos!G30)) -> 0 | G30: =IF(A30="","",IF(D30="",0,D30*Productos!F30)) -> 0 | H30: =IF(A30="","",F30-G30) -> 0 | I30: =IF(A30="","",Productos!J30) -> Agotado
... A34: =IF(Productos!A34="","",Productos!A34) -> P033 | B34: =IF(Productos!B34="","",Productos!B34) -> OUTLET ISOFLEX 5LB CHOCOLATE PEANUT BUTTER | C34: =IF(Productos!$A34="","",Productos!H34) -> 0 | E34: =IF(C34="","",C34-IF(D34="",0,D34)) -> 0 | F34: =IF(A34="","",IF(D34="",0,D34*Productos!G34)) -> 0 | G34: =IF(A34="","",IF(D34="",0,D34*Productos!F34)) -> 0 | H34: =IF(A34="","",F34-G34) -> 0 | I34: =IF(A34="","",Productos!J34) -> Agotado
A35: =IF(Productos!A35="","",Productos!A35) -> P034 | B35: =IF(Productos!B35="","",Productos!B35) -> OUTLET ISOFLEX 5LB CHOCOLATE PEANUT BUTTER | C35: =IF(Productos!$A35="","",Productos!H35) -> 20 | D35: 10 | E35: =IF(C35="","",C35-IF(D35="",0,D35)) -> 10 | F35: =IF(A35="","",IF(D35="",0,D35*Productos!G35)) -> 350 | G35: =IF(A35="","",IF(D35="",0,D35*Productos!F35)) -> 160 | H35: =IF(A35="","",F35-G35) -> 190 | I35: =IF(A35="","",Productos!J35) -> Activo
A36: =IF(Productos!A36="","",Productos!A36) -> P035 | B36: =IF(Productos!B36="","",Productos!B36) -> PREENTRENO BLACK MAMBA 20 SERV GRAPE BUBLEGUM | C36: =IF(Productos!$A36="","",Productos!H36) -> 1 | E36: =IF(C36="","",C36-IF(D36="",0,D36)) -> 1 | F36: =IF(A36="","",IF(D36="",0,D36*Productos!G36)) -> 0 | G36: =IF(A36="","",IF(D36="",0,D36*Productos!F36)) -> 0 | H36: =IF(A36="","",F36-G36) -> 0 | I36: =IF(A36="","",Productos!J36) -> Activo
A37: =IF(Productos!A37="","",Productos!A37) -> P036 | B37: =IF(Productos!B37="","",Productos!B37) -> PREENTRENO BLACK MAMBA 20 SERV GRAPE BUBLEGUM (UND) | C37: =IF(Productos!$A37="","",Productos!H37) -> 15 | E37: =IF(C37="","",C37-IF(D37="",0,D37)) -> 15 | F37: =IF(A37="","",IF(D37="",0,D37*Productos!G37)) -> 0 | G37: =IF(A37="","",IF(D37="",0,D37*Productos!F37)) -> 0 | H37: =IF(A37="","",F37-G37) -> 0 | I37: =IF(A37="","",Productos!J37) -> Activo
A38: =IF(Productos!A38="","",Productos!A38) -> P037 | B38: =IF(Productos!B38="","",Productos!B38) -> PREENTRENO BUCKED UP MOTHER BUCKER 20 SRV MIAMI | C38: =IF(Productos!$A38="","",Productos!H38) -> 20 | E38: =IF(C38="","",C38-IF(D38="",0,D38)) -> 20 | F38: =IF(A38="","",IF(D38="",0,D38*Productos!G38)) -> 0 | G38: =IF(A38="","",IF(D38="",0,D38*Productos!F38)) -> 0 | H38: =IF(A38="","",F38-G38) -> 0 | I38: =IF(A38="","",Productos!J38) -> Activo
A39: =IF(Productos!A39="","",Productos!A39) -> P038 | B39: =IF(Productos!B39="","",Productos!B39) -> PREENTRENO CBUM ESSENTIAL PWO 30 SERV ORANGE | C39: =IF(Productos!$A39="","",Productos!H39) -> 0 | E39: =IF(C39="","",C39-IF(D39="",0,D39)) -> 0 | F39: =IF(A39="","",IF(D39="",0,D39*Productos!G39)) -> 0 | G39: =IF(A39="","",IF(D39="",0,D39*Productos!F39)) -> 0 | H39: =IF(A39="","",F39-G39) -> 0 | I39: =IF(A39="","",Productos!J39) -> Agotado
A40: =IF(Productos!A40="","",Productos!A40) -> P039 | B40: =IF(Productos!B40="","",Productos!B40) -> PREENTRENO CBUM ESSENTIAL PWO 30 SERV RED WHITE AND BUM | C40: =IF(Productos!$A40="","",Productos!H40) -> 25 | E40: =IF(C40="","",C40-IF(D40="",0,D40)) -> 25 | F40: =IF(A40="","",IF(D40="",0,D40*Productos!G40)) -> 0 | G40: =IF(A40="","",IF(D40="",0,D40*Productos!F40)) -> 0 | H40: =IF(A40="","",F40-G40) -> 0 | I40: =IF(A40="","",Productos!J40) -> Activo
A41: =IF(Productos!A41="","",Productos!A41) -> P040 | B41: =IF(Productos!B41="","",Productos!B41) -> PREENTRENO CBUM THAVAGE PWO 40 SERV 6 PEAT | C41: =IF(Productos!$A41="","",Productos!H41) -> 20 | D41: 20 | E41: =IF(C41="","",C41-IF(D41="",0,D41)) -> 0 | F41: =IF(A41="","",IF(D41="",0,D41*Productos!G41)) -> 500 | G41: =IF(A41="","",IF(D41="",0,D41*Productos!F41)) -> 279.06977 | H41: =IF(A41="","",F41-G41) -> 220.93023 | I41: =IF(A41="","",Productos!J41) -> Activo
A42: =IF(Productos!A42="","",Productos!A42) -> P041 | B42: =IF(Productos!B42="","",Productos!B42) -> PREENTRENO HYDE NIGHTMARE PWO 30 SERV BLOOD BERRY | C42: =IF(Productos!$A42="","",Productos!H42) -> 30 | E42: =IF(C42="","",C42-IF(D42="",0,D42)) -> 30 | F42: =IF(A42="","",IF(D42="",0,D42*Productos!G42)) -> 0 | G42: =IF(A42="","",IF(D42="",0,D42*Productos!F42)) -> 0 | H42: =IF(A42="","",F42-G42) -> 0 | I42: =IF(A42="","",Productos!J42) -> Activo
A43: =IF(Productos!A43="","",Productos!A43) -> P042 | B43: =IF(Productos!B43="","",Productos!B43) -> PREENTRENO HYDE NIGHTMARE PWO 30 SERV JAWBREAKER | C43: =IF(Productos!$A43="","",Productos!H43) -> 0 | E43: =IF(C43="","",C43-IF(D43="",0,D43)) -> 0 | F43: =IF(A43="","",IF(D43="",0,D43*Productos!G43)) -> 0 | G43: =IF(A43="","",IF(D43="",0,D43*Productos!F43)) -> 0 | H43: =IF(A43="","",F43-G43) -> 0 | I43: =IF(A43="","",Productos!J43) -> Agotado
A44: =IF(Productos!A44="","",Productos!A44) -> P043 | B44: =IF(Productos!B44="","",Productos!B44) -> PREENTRENO HYDE NIGHTWARE PWO 30 SERV JAWBREAKER | C44: =IF(Productos!$A44="","",Productos!H44) -> 1 | E44: =IF(C44="","",C44-IF(D44="",0,D44)) -> 1 | F44: =IF(A44="","",IF(D44="",0,D44*Productos!G44)) -> 0 | G44: =IF(A44="","",IF(D44="",0,D44*Productos!F44)) -> 0 | H44: =IF(A44="","",F44-G44) -> 0 | I44: =IF(A44="","",Productos!J44) -> Activo
A45: =IF(Productos!A45="","",Productos!A45) -> P044 | B45: =IF(Productos!B45="","",Productos!B45) -> PREENTRENO PANDA | C45: =IF(Productos!$A45="","",Productos!H45) -> 1 | E45: =IF(C45="","",C45-IF(D45="",0,D45)) -> 1 | F45: =IF(A45="","",IF(D45="",0,D45*Productos!G45)) -> 0 | G45: =IF(A45="","",IF(D45="",0,D45*Productos!F45)) -> 0 | H45: =IF(A45="","",F45-G45) -> 0 | I45: =IF(A45="","",Productos!J45) -> Activo
A46: =IF(Productos!A46="","",Productos!A46) -> P045 | B46: =IF(Productos!B46="","",Productos!B46) -> PREENTRENO PANDA FIRST BLOOD PWO 20 SERV SOUR BLUE RASPBERRY | C46: =IF(Productos!$A46="","",Productos!H46) -> 50 | E46: =IF(C46="","",C46-IF(D46="",0,D46)) -> 50 | F46: =IF(A46="","",IF(D46="",0,D46*Productos!G46)) -> 0 | G46: =IF(A46="","",IF(D46="",0,D46*Productos!F46)) -> 0 | H46: =IF(A46="","",F46-G46) -> 0 | I46: =IF(A46="","",Productos!J46) -> Activo
A47: =IF(Productos!A47="","",Productos!A47) -> P046 | B47: =IF(Productos!B47="","",Productos!B47) -> PREENTRENO RYSE LOADED PRE 30 SERV KOOL AID TROPICAL PUNCH | C47: =IF(Productos!$A47="","",Productos!H47) -> 13 | E47: =IF(C47="","",C47-IF(D47="",0,D47)) -> 13 | F47: =IF(A47="","",IF(D47="",0,D47*Productos!G47)) -> 0 | G47: =IF(A47="","",IF(D47="",0,D47*Productos!F47)) -> 0 | H47: =IF(A47="","",F47-G47) -> 0 | I47: =IF(A47="","",Productos!J47) -> Activo
A48: =IF(Productos!A48="","",Productos!A48) -> P047 | B48: =IF(Productos!B48="","",Productos!B48) -> PREENTRENO VENOM | C48: =IF(Productos!$A48="","",Productos!H48) -> 0 | E48: =IF(C48="","",C48-IF(D48="",0,D48)) -> 0 | F48: =IF(A48="","",IF(D48="",0,D48*Productos!G48)) -> 0 | G48: =IF(A48="","",IF(D48="",0,D48*Productos!F48)) -> 0 | H48: =IF(A48="","",F48-G48) -> 0 | I48: =IF(A48="","",Productos!J48) -> Agotado
A49: =IF(Productos!A49="","",Productos!A49) -> P048 | B49: =IF(Productos!B49="","",Productos!B49) -> PREENTRENO VENOM (unidad) | C49: =IF(Productos!$A49="","",Productos!H49) -> 17 | E49: =IF(C49="","",C49-IF(D49="",0,D49)) -> 17 | F49: =IF(A49="","",IF(D49="",0,D49*Productos!G49)) -> 0 | G49: =IF(A49="","",IF(D49="",0,D49*Productos!F49)) -> 0 | H49: =IF(A49="","",F49-G49) -> 0 | I49: =IF(A49="","",Productos!J49) -> Activo
A50: =IF(Productos!A50="","",Productos!A50) -> P049 | B50: =IF(Productos!B50="","",Productos!B50) -> PREETRENO RYSE GODZILLA BACK BERRY LEMONADE | C50: =IF(Productos!$A50="","",Productos!H50) -> 0 | E50: =IF(C50="","",C50-IF(D50="",0,D50)) -> 0 | F50: =IF(A50="","",IF(D50="",0,D50*Productos!G50)) -> 0 | G50: =IF(A50="","",IF(D50="",0,D50*Productos!F50)) -> 0 | H50: =IF(A50="","",F50-G50) -> 0 | I50: =IF(A50="","",Productos!J50) -> Agotado
A51: =IF(Productos!A51="","",Productos!A51) -> P050 | B51: =IF(Productos!B51="","",Productos!B51) -> PREETRENO RYSE GODZILLA BACK BERRY LEMONADE | C51: =IF(Productos!$A51="","",Productos!H51) -> 1 | E51: =IF(C51="","",C51-IF(D51="",0,D51)) -> 1 | F51: =IF(A51="","",IF(D51="",0,D51*Productos!G51)) -> 0 | G51: =IF(A51="","",IF(D51="",0,D51*Productos!F51)) -> 0 | H51: =IF(A51="","",F51-G51) -> 0 | I51: =IF(A51="","",Productos!J51) -> Activo
A52: =IF(Productos!A52="","",Productos!A52) -> P051 | B52: =IF(Productos!B52="","",Productos!B52) -> PROTEIN BAR 12 PCK DOUBLE FUDGE BROWNIE | C52: =IF(Productos!$A52="","",Productos!H52) -> 13 | E52: =IF(C52="","",C52-IF(D52="",0,D52)) -> 13 | F52: =IF(A52="","",IF(D52="",0,D52*Productos!G52)) -> 0 | G52: =IF(A52="","",IF(D52="",0,D52*Productos!F52)) -> 0 | H52: =IF(A52="","",F52-G52) -> 0 | I52: =IF(A52="","",Productos!J52) -> Activo
A53: =IF(Productos!A53="","",Productos!A53) -> P052 | B53: =IF(Productos!B53="","",Productos!B53) -> PROTEINA BAR 12PACK DOUBLE FUDGE BRWNIE | C53: =IF(Productos!$A53="","",Productos!H53) -> 12 | E53: =IF(C53="","",C53-IF(D53="",0,D53)) -> 12 | F53: =IF(A53="","",IF(D53="",0,D53*Productos!G53)) -> 0 | G53: =IF(A53="","",IF(D53="",0,D53*Productos!F53)) -> 0 | H53: =IF(A53="","",F53-G53) -> 0 | I53: =IF(A53="","",Productos!J53) -> Activo
... A55: =IF(Productos!A55="","",Productos!A55) -> P054 | B55: =IF(Productos!B55="","",Productos!B55) -> PROTEINA ISO HD 5 LBS COOKIES BUTTER | C55: =IF(Productos!$A55="","",Productos!H55) -> 0 | E55: =IF(C55="","",C55-IF(D55="",0,D55)) -> 0 | F55: =IF(A55="","",IF(D55="",0,D55*Productos!G55)) -> 0 | G55: =IF(A55="","",IF(D55="",0,D55*Productos!F55)) -> 0 | H55: =IF(A55="","",F55-G55) -> 0 | I55: =IF(A55="","",Productos!J55) -> Agotado
A56: =IF(Productos!A56="","",Productos!A56) -> P055 | B56: =IF(Productos!B56="","",Productos!B56) -> PROTEINA ISO-HD 5 LBS COOKIES BUTTER | C56: =IF(Productos!$A56="","",Productos!H56) -> 60 | D56: 10 | E56: =IF(C56="","",C56-IF(D56="",0,D56)) -> 50 | F56: =IF(A56="","",IF(D56="",0,D56*Productos!G56)) -> 350 | G56: =IF(A56="","",IF(D56="",0,D56*Productos!F56)) -> 157.14286 | H56: =IF(A56="","",F56-G56) -> 192.85714 | I56: =IF(A56="","",Productos!J56) -> Activo
A57: =IF(Productos!A57="","",Productos!A57) -> P056 | B57: =IF(Productos!B57="","",Productos!B57) -> PROTEINA ISOFIT 5 LBS STRAWBERRY AND CREAM | C57: =IF(Productos!$A57="","",Productos!H57) -> 1 | E57: =IF(C57="","",C57-IF(D57="",0,D57)) -> 1 | F57: =IF(A57="","",IF(D57="",0,D57*Productos!G57)) -> 0 | G57: =IF(A57="","",IF(D57="",0,D57*Productos!F57)) -> 0 | H57: =IF(A57="","",F57-G57) -> 0 | I57: =IF(A57="","",Productos!J57) -> Activo
A58: =IF(Productos!A58="","",Productos!A58) -> P057 | B58: =IF(Productos!B58="","",Productos!B58) -> PROTEINA ISOPHORM 5 LBS BLUEBERR ICE CREAM | C58: =IF(Productos!$A58="","",Productos!H58) -> 1 | E58: =IF(C58="","",C58-IF(D58="",0,D58)) -> 1 | F58: =IF(A58="","",IF(D58="",0,D58*Productos!G58)) -> 0 | G58: =IF(A58="","",IF(D58="",0,D58*Productos!F58)) -> 0 | H58: =IF(A58="","",F58-G58) -> 0 | I58: =IF(A58="","",Productos!J58) -> Activo
A59: =IF(Productos!A59="","",Productos!A59) -> P058 | B59: =IF(Productos!B59="","",Productos!B59) -> PROTEINA ISOPURE ZERO CARB 4.5 LBS VAINILLA | C59: =IF(Productos!$A59="","",Productos!H59) -> 1 | D59: 1 | E59: =IF(C59="","",C59-IF(D59="",0,D59)) -> 0 | F59: =IF(A59="","",IF(D59="",0,D59*Productos!G59)) -> 1700 | G59: =IF(A59="","",IF(D59="",0,D59*Productos!F59)) -> 1500 | H59: =IF(A59="","",F59-G59) -> 200 | I59: =IF(A59="","",Productos!J59) -> Agotado
A60: =IF(Productos!A60="","",Productos!A60) -> P059 | B60: =IF(Productos!B60="","",Productos!B60) -> PROTEINA RAW CBUM ITHOLATE 5 LBS COOKIES & CREAM (UND) | C60: =IF(Productos!$A60="","",Productos!H60) -> 20 | D60: 10 | E60: =IF(C60="","",C60-IF(D60="",0,D60)) -> 10 | F60: =IF(A60="","",IF(D60="",0,D60*Productos!G60)) -> 350 | G60: =IF(A60="","",IF(D60="",0,D60*Productos!F60)) -> 200 | H60: =IF(A60="","",F60-G60) -> 150 | I60: =IF(A60="","",Productos!J60) -> Activo
A61: =IF(Productos!A61="","",Productos!A61) -> P060 | B61: =IF(Productos!B61="","",Productos!B61) -> RAW CBUM ESSENTIAL PWO 30 SERV JAMAICA *EDICION LIMITADA* | C61: =IF(Productos!$A61="","",Productos!H61) -> 33 | D61: 20 | E61: =IF(C61="","",C61-IF(D61="",0,D61)) -> 13 | F61: =IF(A61="","",IF(D61="",0,D61*Productos!G61)) -> 500 | G61: =IF(A61="","",IF(D61="",0,D61*Productos!F61)) -> 254.54545 | H61: =IF(A61="","",F61-G61) -> 245.45455 | I61: =IF(A61="","",Productos!J61) -> Activo
A62: =IF(Productos!A62="","",Productos!A62) -> P061 | B62: =IF(Productos!B62="","",Productos!B62) -> RAW CREATINE MONOHYDRATE 100 SERV UNFLAVORED | C62: =IF(Productos!$A62="","",Productos!H62) -> 1 | E62: =IF(C62="","",C62-IF(D62="",0,D62)) -> 1 | F62: =IF(A62="","",IF(D62="",0,D62*Productos!G62)) -> 0 | G62: =IF(A62="","",IF(D62="",0,D62*Productos!F62)) -> 0 | H62: =IF(A62="","",F62-G62) -> 0 | I62: =IF(A62="","",Productos!J62) -> Activo
A63: =IF(Productos!A63="","",Productos!A63) -> P062 | B63: =IF(Productos!B63="","",Productos!B63) -> RAW CREATINE MONOHYDRATE 250 SERV UNFLAVORED *NUEVO* | C63: =IF(Productos!$A63="","",Productos!H63) -> 0 | E63: =IF(C63="","",C63-IF(D63="",0,D63)) -> 0 | F63: =IF(A63="","",IF(D63="",0,D63*Productos!G63)) -> 0 | G63: =IF(A63="","",IF(D63="",0,D63*Productos!F63)) -> 0 | H63: =IF(A63="","",F63-G63) -> 0 | I63: =IF(A63="","",Productos!J63) -> Agotado
A64: =IF(Productos!A64="","",Productos!A64) -> P063 | B64: =IF(Productos!B64="","",Productos!B64) -> RAW MY COOKIE DEALER 113 G 12 PACK MILK & COOKIES | C64: =IF(Productos!$A64="","",Productos!H64) -> 22 | D64: 22 | E64: =IF(C64="","",C64-IF(D64="",0,D64)) -> 0 | F64: =IF(A64="","",IF(D64="",0,D64*Productos!G64)) -> 1540 | G64: =IF(A64="","",IF(D64="",0,D64*Productos!F64)) -> 1100 | H64: =IF(A64="","",F64-G64) -> 440 | I64: =IF(A64="","",Productos!J64) -> Activo
A65: =IF(Productos!A65="","",Productos!A65) -> P064 | B65: =IF(Productos!B65="","",Productos!B65) -> TESTROL GOGA TESTROL GOLD 60 TABSLD | C65: =IF(Productos!$A65="","",Productos!H65) -> 1 | E65: =IF(C65="","",C65-IF(D65="",0,D65)) -> 1 | F65: =IF(A65="","",IF(D65="",0,D65*Productos!G65)) -> 0 | G65: =IF(A65="","",IF(D65="",0,D65*Productos!F65)) -> 0 | H65: =IF(A65="","",F65-G65) -> 0 | I65: =IF(A65="","",Productos!J65) -> Activo
A66: =IF(Productos!A66="","",Productos!A66) -> P065 | B66: =IF(Productos!B66="","",Productos!B66) -> THINK HIGH PROTEIN 10 BARS CHUNKY PEANUT BUTTER | C66: =IF(Productos!$A66="","",Productos!H66) -> 0 | E66: =IF(C66="","",C66-IF(D66="",0,D66)) -> 0 | F66: =IF(A66="","",IF(D66="",0,D66*Productos!G66)) -> 0 | G66: =IF(A66="","",IF(D66="",0,D66*Productos!F66)) -> 0 | H66: =IF(A66="","",F66-G66) -> 0 | I66: =IF(A66="","",Productos!J66) -> Agotado
A67: =IF(Productos!A67="","",Productos!A67) -> P066 | B67: =IF(Productos!B67="","",Productos!B67) -> THINK HIGH PROTEIN 10 BARS COOKIES & CREAM | C67: =IF(Productos!$A67="","",Productos!H67) -> 0 | E67: =IF(C67="","",C67-IF(D67="",0,D67)) -> 0 | F67: =IF(A67="","",IF(D67="",0,D67*Productos!G67)) -> 0 | G67: =IF(A67="","",IF(D67="",0,D67*Productos!F67)) -> 0 | H67: =IF(A67="","",F67-G67) -> 0 | I67: =IF(A67="","",Productos!J67) -> Agotado
A68: =IF(Productos!A68="","",Productos!A68) -> P067 | B68: =IF(Productos!B68="","",Productos!B68) -> TOTAL WAR BLACK OPS 20 SERV TIGERS BLOOD *CAD 07/27* | C68: =IF(Productos!$A68="","",Productos!H68) -> 25 | E68: =IF(C68="","",C68-IF(D68="",0,D68)) -> 25 | F68: =IF(A68="","",IF(D68="",0,D68*Productos!G68)) -> 0 | G68: =IF(A68="","",IF(D68="",0,D68*Productos!F68)) -> 0 | H68: =IF(A68="","",F68-G68) -> 0 | I68: =IF(A68="","",Productos!J68) -> Activo
A69: =IF(Productos!A69="","",Productos!A69) -> P068 | B69: =IF(Productos!B69="","",Productos!B69) -> VASOS SHAKERS | C69: =IF(Productos!$A69="","",Productos!H69) -> 3 | D69: 2 | E69: =IF(C69="","",C69-IF(D69="",0,D69)) -> 1 | F69: =IF(A69="","",IF(D69="",0,D69*Productos!G69)) -> 260 | G69: =IF(A69="","",IF(D69="",0,D69*Productos!F69)) -> 200 | H69: =IF(A69="","",F69-G69) -> 60 | I69: =IF(A69="","",Productos!J69) -> Activo
A70: =IF(Productos!A70="","",Productos!A70) | B70: =IF(Productos!B70="","",Productos!B70) | C70: =IF(Productos!$A70="","",Productos!H70) | E70: =IF(C70="","",C70-IF(D70="",0,D70)) | F70: =IF(A70="","",IF(D70="",0,D70*Productos!G70)) | G70: =IF(A70="","",IF(D70="",0,D70*Productos!F70)) | H70: =IF(A70="","",F70-G70) | I70: =IF(A70="","",Productos!J70)
A71: =IF(Productos!A71="","",Productos!A71) | B71: =IF(Productos!B71="","",Productos!B71) | C71: =IF(Productos!$A71="","",Productos!H71) | E71: =IF(C71="","",C71-IF(D71="",0,D71)) | F71: =IF(A71="","",IF(D71="",0,D71*Productos!G71)) | G71: =IF(A71="","",IF(D71="",0,D71*Productos!F71)) | H71: =IF(A71="","",F71-G71) | I71: =IF(A71="","",Productos!J71)
A72: =IF(Productos!A72="","",Productos!A72) | B72: =IF(Productos!B72="","",Productos!B72) | C72: =IF(Productos!$A72="","",Productos!H72) | E72: =IF(C72="","",C72-IF(D72="",0,D72)) | F72: =IF(A72="","",IF(D72="",0,D72*Productos!G72)) | G72: =IF(A72="","",IF(D72="",0,D72*Productos!F72)) | H72: =IF(A72="","",F72-G72) | I72: =IF(A72="","",Productos!J72)
A73: =IF(Productos!A73="","",Productos!A73) | B73: =IF(Productos!B73="","",Productos!B73) | C73: =IF(Productos!$A73="","",Productos!H73) | E73: =IF(C73="","",C73-IF(D73="",0,D73)) | F73: =IF(A73="","",IF(D73="",0,D73*Productos!G73)) | G73: =IF(A73="","",IF(D73="",0,D73*Productos!F73)) | H73: =IF(A73="","",F73-G73) | I73: =IF(A73="","",Productos!J73)
A74: =IF(Productos!A74="","",Productos!A74) | B74: =IF(Productos!B74="","",Productos!B74) | C74: =IF(Productos!$A74="","",Productos!H74) | E74: =IF(C74="","",C74-IF(D74="",0,D74)) | F74: =IF(A74="","",IF(D74="",0,D74*Productos!G74)) | G74: =IF(A74="","",IF(D74="",0,D74*Productos!F74)) | H74: =IF(A74="","",F74-G74) | I74: =IF(A74="","",Productos!J74)
A75: =IF(Productos!A75="","",Productos!A75) | B75: =IF(Productos!B75="","",Productos!B75) | C75: =IF(Productos!$A75="","",Productos!H75) | E75: =IF(C75="","",C75-IF(D75="",0,D75)) | F75: =IF(A75="","",IF(D75="",0,D75*Productos!G75)) | G75: =IF(A75="","",IF(D75="",0,D75*Productos!F75)) | H75: =IF(A75="","",F75-G75) | I75: =IF(A75="","",Productos!J75)
A76: =IF(Productos!A76="","",Productos!A76) | B76: =IF(Productos!B76="","",Productos!B76) | C76: =IF(Productos!$A76="","",Productos!H76) | E76: =IF(C76="","",C76-IF(D76="",0,D76)) | F76: =IF(A76="","",IF(D76="",0,D76*Productos!G76)) | G76: =IF(A76="","",IF(D76="",0,D76*Productos!F76)) | H76: =IF(A76="","",F76-G76) | I76: =IF(A76="","",Productos!J76)
A77: =IF(Productos!A77="","",Productos!A77) | B77: =IF(Productos!B77="","",Productos!B77) | C77: =IF(Productos!$A77="","",Productos!H77) | E77: =IF(C77="","",C77-IF(D77="",0,D77)) | F77: =IF(A77="","",IF(D77="",0,D77*Productos!G77)) | G77: =IF(A77="","",IF(D77="",0,D77*Productos!F77)) | H77: =IF(A77="","",F77-G77) | I77: =IF(A77="","",Productos!J77)
A78: =IF(Productos!A78="","",Productos!A78) | B78: =IF(Productos!B78="","",Productos!B78) | C78: =IF(Productos!$A78="","",Productos!H78) | E78: =IF(C78="","",C78-IF(D78="",0,D78)) | F78: =IF(A78="","",IF(D78="",0,D78*Productos!G78)) | G78: =IF(A78="","",IF(D78="",0,D78*Productos!F78)) | H78: =IF(A78="","",F78-G78) | I78: =IF(A78="","",Productos!J78)
A79: =IF(Productos!A79="","",Productos!A79) | B79: =IF(Productos!B79="","",Productos!B79) | C79: =IF(Productos!$A79="","",Productos!H79) | E79: =IF(C79="","",C79-IF(D79="",0,D79)) | F79: =IF(A79="","",IF(D79="",0,D79*Productos!G79)) | G79: =IF(A79="","",IF(D79="",0,D79*Productos!F79)) | H79: =IF(A79="","",F79-G79) | I79: =IF(A79="","",Productos!J79)
A80: =IF(Productos!A80="","",Productos!A80) | B80: =IF(Productos!B80="","",Productos!B80) | C80: =IF(Productos!$A80="","",Productos!H80) | E80: =IF(C80="","",C80-IF(D80="",0,D80)) | F80: =IF(A80="","",IF(D80="",0,D80*Productos!G80)) | G80: =IF(A80="","",IF(D80="",0,D80*Productos!F80)) | H80: =IF(A80="","",F80-G80) | I80: =IF(A80="","",Productos!J80)
A81: =IF(Productos!A81="","",Productos!A81) | B81: =IF(Productos!B81="","",Productos!B81) | C81: =IF(Productos!$A81="","",Productos!H81) | E81: =IF(C81="","",C81-IF(D81="",0,D81)) | F81: =IF(A81="","",IF(D81="",0,D81*Productos!G81)) | G81: =IF(A81="","",IF(D81="",0,D81*Productos!F81)) | H81: =IF(A81="","",F81-G81) | I81: =IF(A81="","",Productos!J81)
... A1000: =IF(Productos!A1000="","",Productos!A1000) | B1000: =IF(Productos!B1000="","",Productos!B1000) | C1000: =IF(Productos!$A1000="","",Productos!H1000) | E1000: =IF(C1000="","",C1000-IF(D1000="",0,D1000)) | F1000: =IF(A1000="","",IF(D1000="",0,D1000*Productos!G1000)) | G1000: =IF(A1000="","",IF(D1000="",0,D1000*Productos!F1000)) | H1000: =IF(A1000="","",F1000-G1000) | I1000: =IF(A1000="","",Productos!J1000)
B1002: TOTAL | E1002: =SUMIFS(E$2:E1000,A$2:A1000,"<>") -> 356 | F1002: =SUMIFS(F$2:F1000,A$2:A1000,"<>") -> 8840 | G1002: =SUMIFS(G$2:G1000,A$2:A1000,"<>") -> 6529.0914 | H1002: =SUMIFS(H$2:H1000,A$2:A1000,"<>") -> 2310.9086

Sheet Productos Vendidos
A1: PRODUCTOS VENDIDOS | I1: Resumen de Negocio
A2: Producto | B2: Piezas vendidas | C2: Costo del producto | D2: Precio al público | E2: Total vendido | F2: Ganancia | I2: Total vendido | J2: =Resumen!B2 -> 8840
A3: {=IFERROR(_xlfn._xlws.FILTER(_xlfn.HSTACK(Ventas!B2:B1000,Ventas!D2:D1000,Productos!E2:E1000,Productos!G2:G1000,Ventas!F2:F1000,Ventas!H2:H1000),(Ventas!D2:D1000<>"")*(Ventas!D2:D1000>0),"Sin ventas registradas"),"Sin ventas registradas")} -> BEBIDA CELSIUS | B3: 2 | C3: 600 | D3: 70 | E3: 140 | F3: 40 | I3: Dinero para resurtir | J3: =Resumen!B3 -> 6529.0914
A4: BLOOM SURTIDO | B4: 10 | C4: 550 | D4: 65 | E4: 650 | F4: 191.66667 | I4: Ganancia pura | J4: =Resumen!B4 -> 2310.9086
A5: BSN PROTEIN CRIPS 12 BARS VANILLA MARSHMALLOW *OFERTA* | B5: 12 | C5: 600 | D5: 65 | E5: 780 | F5: 180 | I5: Fernando | J5: =Resumen!B5 -> 770.31
A6: CREATINA BIRDMAN | B6: 3 | C6: 780 | D6: 430 | E6: 1290 | F6: 120 | I6: Roberto | J6: =Resumen!B6 -> 770.31
A7: CREATINA BIRDMAN CON ELECTROLIT | B7: 1 | C7: 350 | D7: 430 | E7: 430 | F7: 80 | I7: Isak | J7: =Resumen!B7 -> 770.28859
A8: OUTLET ISOFLEX 5LB CHOCOLATE PEANUT BUTTER | B8: 10 | C8: 1120 | D8: 35 | E8: 350 | F8: 190
A9: PREENTRENO CBUM THAVAGE PWO 40 SERV 6 PEAT | B9: 20 | C9: 600 | D9: 25 | E9: 500 | F9: 220.93023
A10: PROTEINA ISO-HD 5 LBS COOKIES BUTTER | B10: 10 | C10: 1100 | D10: 35 | E10: 350 | F10: 192.85714
A11: PROTEINA ISOPURE ZERO CARB 4.5 LBS VAINILLA | B11: 1 | C11: 1500 | D11: 1700 | E11: 1700 | F11: 200
A12: PROTEINA RAW CBUM ITHOLATE 5 LBS COOKIES & CREAM (UND) | B12: 10 | C12: 1400 | D12: 35 | E12: 350 | F12: 150
A13: RAW CBUM ESSENTIAL PWO 30 SERV JAMAICA *EDICION LIMITADA* | B13: 20 | C13: 420 | D13: 25 | E13: 500 | F13: 245.45455
A14: RAW MY COOKIE DEALER 113 G 12 PACK MILK & COOKIES | B14: 22 | C14: 600 | D14: 70 | E14: 1540 | F14: 440
A15: VASOS SHAKERS | B15: 2 | C15: 300 | D15: 130 | E15: 260 | F15: 60

Sheet Reparto
A1: ID | B1: Producto | C1: Ganancia pura | D1: Fernando | E1: Roberto | F1: Isak
A2: =IF(Productos!A2="","",Productos!A2) -> P001 | B2: =IF(Productos!B2="","",Productos!B2) -> AN ABE ENERGY DRINK 11.2 OZ 12PK TANG ORANGE | C2: =IF(A2="","",Ventas!H2) -> 0 | D2: =IF(A2="","",ROUND(C2/3,2)) -> 0 | E2: =IF(A2="","",ROUND(C2/3,2)) -> 0 | F2: =IF(A2="","",C2-D2-E2) -> 0
A3: =IF(Productos!A3="","",Productos!A3) -> P002 | B3: =IF(Productos!B3="","",Productos!B3) -> ARMADA ASHWAGANDHA + L-TEANINA 600 MG 90 CAPS | C3: =IF(A3="","",Ventas!H3) -> 0 | D3: =IF(A3="","",ROUND(C3/3,2)) -> 0 | E3: =IF(A3="","",ROUND(C3/3,2)) -> 0 | F3: =IF(A3="","",C3-D3-E3) -> 0
A4: =IF(Productos!A4="","",Productos!A4) -> P003 | B4: =IF(Productos!B4="","",Productos!B4) -> ARMADA CITRATO DE MAGNESIO 1000 MG 100 CAPS | C4: =IF(A4="","",Ventas!H4) -> 0 | D4: =IF(A4="","",ROUND(C4/3,2)) -> 0 | E4: =IF(A4="","",ROUND(C4/3,2)) -> 0 | F4: =IF(A4="","",C4-D4-E4) -> 0
A5: =IF(Productos!A5="","",Productos!A5) -> P004 | B5: =IF(Productos!B5="","",Productos!B5) -> BEBIDA CELSIUS | C5: =IF(A5="","",Ventas!H5) -> 40 | D5: =IF(A5="","",ROUND(C5/3,2)) -> 13.33 | E5: =IF(A5="","",ROUND(C5/3,2)) -> 13.33 | F5: =IF(A5="","",C5-D5-E5) -> 13.34
A6: =IF(Productos!A6="","",Productos!A6) -> P005 | B6: =IF(Productos!B6="","",Productos!B6) -> BLOOM 25 SERV PAQUETE | C6: =IF(A6="","",Ventas!H6) -> 0 | D6: =IF(A6="","",ROUND(C6/3,2)) -> 0 | E6: =IF(A6="","",ROUND(C6/3,2)) -> 0 | F6: =IF(A6="","",C6-D6-E6) -> 0
A7: =IF(Productos!A7="","",Productos!A7) -> P006 | B7: =IF(Productos!B7="","",Productos!B7) -> BLOOM SPAERKALING ENERGY 12OZ PEACH WATERMELON | C7: =IF(A7="","",Ventas!H7) -> 0 | D7: =IF(A7="","",ROUND(C7/3,2)) -> 0 | E7: =IF(A7="","",ROUND(C7/3,2)) -> 0 | F7: =IF(A7="","",C7-D7-E7) -> 0
A8: =IF(Productos!A8="","",Productos!A8) -> P007 | B8: =IF(Productos!B8="","",Productos!B8) -> BLOOM SPARKLING ENERGY 12OZ PEACH MANGO | C8: =IF(A8="","",Ventas!H8) -> 0 | D8: =IF(A8="","",ROUND(C8/3,2)) -> 0 | E8: =IF(A8="","",ROUND(C8/3,2)) -> 0 | F8: =IF(A8="","",C8-D8-E8) -> 0
A9: =IF(Productos!A9="","",Productos!A9) -> P008 | B9: =IF(Productos!B9="","",Productos!B9) -> BLOOM SPEARKLING ENERGY 12OZ PEACH LEMONS | C9: =IF(A9="","",Ventas!H9) -> 0 | D9: =IF(A9="","",ROUND(C9/3,2)) -> 0 | E9: =IF(A9="","",ROUND(C9/3,2)) -> 0 | F9: =IF(A9="","",C9-D9-E9) -> 0
A10: =IF(Productos!A10="","",Productos!A10) -> P009 | B10: =IF(Productos!B10="","",Productos!B10) -> BLOOM SURTIDO | C10: =IF(A10="","",Ventas!H10) -> 191.66667 | D10: =IF(A10="","",ROUND(C10/3,2)) -> 63.89 | E10: =IF(A10="","",ROUND(C10/3,2)) -> 63.89 | F10: =IF(A10="","",C10-D10-E10) -> 63.886667
A11: =IF(Productos!A11="","",Productos!A11) -> P010 | B11: =IF(Productos!B11="","",Productos!B11) -> BSN NO-XPLODE VASO PUMP 24 SERV PINEAPPLE PUMP | C11: =IF(A11="","",Ventas!H11) -> 0 | D11: =IF(A11="","",ROUND(C11/3,2)) -> 0 | E11: =IF(A11="","",ROUND(C11/3,2)) -> 0 | F11: =IF(A11="","",C11-D11-E11) -> 0
A12: =IF(Productos!A12="","",Productos!A12) -> P011 | B12: =IF(Productos!B12="","",Productos!B12) -> BSN PROTEIN CRIPS 12 BARS VANILLA MARSHMALLOW *OFERTA* | C12: =IF(A12="","",Ventas!H12) -> 180 | D12: =IF(A12="","",ROUND(C12/3,2)) -> 60 | E12: =IF(A12="","",ROUND(C12/3,2)) -> 60 | F12: =IF(A12="","",C12-D12-E12) -> 60
A13: =IF(Productos!A13="","",Productos!A13) -> P012 | B13: =IF(Productos!B13="","",Productos!B13) -> CBUM ESSENTIAL PWO 30 SERV BLUE RASPBERRY | C13: =IF(A13="","",Ventas!H13) -> 0 | D13: =IF(A13="","",ROUND(C13/3,2)) -> 0 | E13: =IF(A13="","",ROUND(C13/3,2)) -> 0 | F13: =IF(A13="","",C13-D13-E13) -> 0
... A1000: =IF(Productos!A1000="","",Productos!A1000) | B1000: =IF(Productos!B1000="","",Productos!B1000) | C1000: =IF(A1000="","",Ventas!H1000) | D1000: =IF(A1000="","",ROUND(C1000/3,2)) | E1000: =IF(A1000="","",ROUND(C1000/3,2)) | F1000: =IF(A1000="","",C1000-D1000-E1000)
B1002: TOTAL | C1002: =SUM(C$2:C1000) -> 2310.9086 | D1002: =SUM(D$2:D1000) -> 770.31 | E1002: =SUM(E$2:E1000) -> 770.31 | F1002: =SUM(F$2:F1000) -> 770.28859

Sheet Cómo usar
A1: 📖 Cómo usar este archivo
A3: ✅ AGREGAR NUEVO PRODUCTO:
A4: 1. Ve a la hoja "Productos"
A5: 2. En la siguiente fila vacía, ingresa el nombre del producto en columna B
A6: 3. El ID se genera AUTOMÁTICAMENTE (P010, P011, etc.)
A7: 4. Llena: Lotes, Piezas por producto, Costo, Precio y Stock inicial
A8: 5. ¡El producto aparecerá automáticamente en Ventas y Reparto!
A10: 📝 REGISTRAR VENTAS:
A11: • En la hoja "Ventas", solo edita la columna "Piezas vendidas" (D)
A12: • Todo lo demás se calcula automáticamente
A14: ⚠️ ALERTAS:
A15: • Cuando el Stock actual sea 2 o menos, la celda se pone ROJA

Sheet Cortes Semanales
A1: 📊 Seguimiento Semanal de Cortes
A2: Concepto | B2: Semana 1 | C2: Fecha | D2: Semana 2 | E2: Fecha | F2: Semana 3 | G2: Fecha | H2: Semana 4 | I2: Fecha
A5: 💰 Ganancia | B5: 1327 | C5: 46140 | D5: 0
A6: 🛒 Total Vendido | B6: 3190 | C6: 46140
A8: 📈 ACUMULADOS
A9: Ganancia Total: | B9: =B5+D5+F5+H5 -> 1327
A10: Ventas Total: | B10: =B6+D6+F6+H6 -> 3190
A12: 📝 Instrucciones:
A13: • Ingresa la ganancia y total vendido de cada semana cuando hagas corte
A14: • Registra la fecha del corte en la columna correspondiente
A15: • Los acumulados se calculan automáticamente
